nothingtoseehere/__init__.py
nothingtoseehere/neuromotor_input.py
nothingtoseehere/py.typed
nothingtoseehere-1.2.0.dist-info/licenses/LICENSE
nothingtoseehere-1.2.0.dist-info/METADATA
nothingtoseehere-1.2.0.dist-info/WHEEL
nothingtoseehere-1.2.0.dist-info/top_level.txt
nothingtoseehere-1.2.0.dist-info/RECORD
