Metadata-Version: 2.4
Name: nothingtoseehere
Version: 1.2.0
Summary: Human-like mouse and keyboard input simulation based on neuromotor research. Nothing to see here. 🐭
Author: Super44
License: Apache-2.0
Project-URL: Homepage, https://github.com/Super-44/nothingtoseehere
Project-URL: Changelog, https://github.com/Super-44/nothingtoseehere/releases
Project-URL: Issues, https://github.com/Super-44/nothingtoseehere/issues
Project-URL: CI, https://github.com/Super-44/nothingtoseehere/actions
Keywords: mouse,keyboard,automation,human-like,bot-detection,neuromotor,fitts-law
Classifier: Development Status :: 3 - Alpha
Classifier: Intended Audience :: Developers
Classifier: Operating System :: OS Independent
Classifier: Programming Language :: Python :: 3
Classifier: Programming Language :: Python :: 3.10
Classifier: Programming Language :: Python :: 3.11
Classifier: Programming Language :: Python :: 3.12
Classifier: Programming Language :: Python :: 3.13
Classifier: Programming Language :: Python :: 3.14
Classifier: Topic :: Scientific/Engineering :: Human Machine Interfaces
Classifier: Topic :: Software Development :: Testing
Classifier: Topic :: Software Development :: Testing :: Traffic Generation
Classifier: Topic :: Software Development :: Libraries :: Python Modules
Classifier: Topic :: Scientific/Engineering :: Artificial Life
Classifier: Typing :: Typed
Requires-Python: >=3.10
License-File: LICENSE
Requires-Dist: numpy>=1.24.0
Requires-Dist: scipy>=1.10.0
Requires-Dist: pyautogui>=0.9.54
Provides-Extra: browser
Requires-Dist: nodriver>=0.38; extra == "browser"
Provides-Extra: dev
Requires-Dist: pytest; extra == "dev"
Dynamic: license-file
